{
    "state_machine": "GenericStateMachine",
    "type": "World",
    "comment": "Door of Dragon Force: Raging Horned Demon",
    "quest_id": 21000099,
    "base_level": 70,
    "minimum_item_rank": 0,
    "discoverable": false,
    "area_id": "BloodbaneIsle",
    "rewards": [
        {
            "type": "wallet",
            "wallet_type": "Gold",
            "amount": 2309
        },
        {
            "type": "wallet",
            "wallet_type": "RiftPoints",
            "amount": 300
        },
        {
            "type": "exp",
            "amount": 18420
        },
        {
            "type": "select",
            "loot_pool": [
                {
                    "item_id": 11779,
                    "num": 1
                },
                {
                    "item_id": 9364,
                    "num": 3
                },
                {
                    "item_id": 41,
                    "num": 3
                }
            ]
        }
    ],
    "enemy_groups" : [
        {
            "stage_id": {
                "id": 443,
                "group_id": 2
            },
            "enemies": [
                {
                    "enemy_id": "0x015850",
                    "level": 70,
                    "exp": 85000,
                    "is_boss": true
                },
                {
                    "enemy_id": "0x015851",
                    "level": 70,
                    "exp": 85000,
                    "is_boss": true
                }
            ]
        }
    ],
    "blocks": [
        {
            "type": "DiscoverEnemy",
            "groups": [0]
        },
        {
            "type": "KillGroup",
            "announce_type": "Accept",
            "reset_group": false,
            "groups": [0]
        }
    ]
}
